mudder/__init__.py
mudder/py.typed
mudder-0.3.1.dist-info/METADATA
mudder-0.3.1.dist-info/WHEEL
mudder-0.3.1.dist-info/licenses/LICENSE.md
mudder-0.3.1.dist-info/RECORD
