Metadata-Version: 2.4
Name: mudder
Version: 0.3.1
Summary: Python port of mudderjs
Project-URL: Homepage, https://github.com/fellowapp/mudder-py
Project-URL: Repository, https://github.com/fellowapp/mudder-py
Project-URL: Changelog, https://github.com/fellowapp/mudder-py/releases
Author-email: Patrick Gingras <775.pg.12@gmail.com>
License: BSD-3-Clause
License-File: LICENSE.md
Classifier: Development Status :: 5 - Production/Stable
Classifier: Intended Audience :: Developers
Classifier: License :: OSI Approved :: BSD License
Classifier: Operating System :: OS Independent
Classifier: Programming Language :: Python
Classifier: Programming Language :: Python :: 3 :: Only
Classifier: Programming Language :: Python :: 3.10
Classifier: Programming Language :: Python :: 3.11
Classifier: Programming Language :: Python :: 3.12
Classifier: Programming Language :: Python :: 3.13
Classifier: Topic :: Software Development :: Libraries :: Python Modules
Classifier: Typing :: Typed
Requires-Python: >=3.10
